scrapd/__init__.py
scrapd/main.py
scrapd/cli/__init__.py
scrapd/cli/base.py
scrapd/cli/cli.py
scrapd/core/__init__.py
scrapd/core/apd.py
scrapd/core/article.py
scrapd/core/constant.py
scrapd/core/date_utils.py
scrapd/core/deceased.py
scrapd/core/formatter.py
scrapd/core/model.py
scrapd/core/regex.py
scrapd/core/version.py
scrapd-3.1.2.data/data/etc/bash_completion.d/scrapd-complete.sh
scrapd-3.1.2.dist-info/LICENSE
scrapd-3.1.2.dist-info/METADATA
scrapd-3.1.2.dist-info/WHEEL
scrapd-3.1.2.dist-info/entry_points.txt
scrapd-3.1.2.dist-info/pbr.json
scrapd-3.1.2.dist-info/top_level.txt
scrapd-3.1.2.dist-info/RECORD
