Metadata-Version: 2.1
Name: scrapd
Version: 3.1.2
Summary: Extract data from APD news site
Home-page: https://www.scrapd.org
Author: Rémy Greinhofer
Author-email: info@scrapd.org
License: UNKNOWN
Platform: UNKNOWN
Classifier: Development Status :: 5 - Production/Stable
Classifier: Environment :: Console
Classifier: Intended Audience :: End Users/Desktop
Classifier: License :: OSI Approved :: MIT License
Classifier: Operating System :: POSIX :: Linux
Classifier: Operating System :: MacOS :: MacOS X
Classifier: Operating System :: Microsoft :: Windows
Classifier: Programming Language :: Python
Classifier: Programming Language :: Python :: 3 :: Only
Classifier: Programming Language :: Python :: 3.7
Classifier: Topic :: Utilities
Requires-Dist: aiohttp (==3.6.1)
Requires-Dist: beautifulsoup4 (==4.8.1)
Requires-Dist: click (==7.0)
Requires-Dist: dateparser (==0.7.2)
Requires-Dist: loguru (==0.3.2)
Requires-Dist: pbr (>=5.2.0)
Requires-Dist: pydantic (==0.32.2)
Requires-Dist: tenacity (==5.1.1)
